firmware_content_extractor/__init__.py
firmware_content_extractor/cli.py
firmware_content_extractor/direct.py
firmware_content_extractor/fasturl.py
firmware_content_extractor/network.py
firmware_content_extractor/parser.py
firmware_content_extractor/payload.py
fcetool-1.0.3.dist-info/METADATA
fcetool-1.0.3.dist-info/WHEEL
fcetool-1.0.3.dist-info/entry_points.txt
fcetool-1.0.3.dist-info/top_level.txt
fcetool-1.0.3.dist-info/RECORD
